nolead/__init__.py
nolead/core.py
nolead/logging.py
nolead/visualization.py
nolead-0.2.0.dist-info/licenses/LICENSE
tests/__init__.py
tests/test_core.py
tests/test_parallel.py
tests/test_parameters.py
nolead-0.2.0.dist-info/METADATA
nolead-0.2.0.dist-info/WHEEL
nolead-0.2.0.dist-info/top_level.txt
nolead-0.2.0.dist-info/RECORD
