Metadata-Version: 2.4
Name: nolead
Version: 0.2.0
Summary: A lightweight pipeline orchestration library inspired by Luigi
Author: Rui Vieira
Author-email: Rui Vieira <ruidevieira@googlemail.com>
Project-URL: Homepage, https://github.com/ruivieira/nolead
Project-URL: Bug Tracker, https://github.com/ruivieira/nolead/issues
Classifier: Programming Language :: Python :: 3
Classifier: License :: OSI Approved :: MIT License
Classifier: Operating System :: OS Independent
Requires-Python: >=3.6
License-File: LICENSE
Dynamic: author
Dynamic: license-file
Dynamic: requires-python
